[
  {
    "bayramNamazVakti": {
      "KurbanBayramNamaziHTarihi": "10 Zilhicce 1446",
      "KurbanBayramNamaziSaati": "06:42:00",
      "KurbanBayramNamaziTarihi": "6 Haziran 2025 Cuma",
      "RamazanBayramNamaziHTarihi": "1 Şevval 1446",
      "RamazanBayramNamaziSaati": "06:54:00",
      "RamazanBayramNamaziTarihi": "30 Mart 2025 Pazar"
    },
    "ilceBilgisi": {
      "CografiKibleAcisi": "59",
      "IlceAdi": "ABA",
      "IlceAdiEn": null,
      "IlceID": "15582",
      "KabeyeUzaklik": "3941",
      "KibleAcisi": "62",
      "SehirAdi": "NIJERYA",
      "SehirAdiEn": null,
      "UlkeAdi": "NIJERYA",
      "UlkeAdiEn": null
    }
  },
  {
    "bayramNamazVakti": {
      "KurbanBayramNamaziHTarihi": "10 Zilhicce 1446",
      "KurbanBayramNamaziSaati": "06:36:00",
      "KurbanBayramNamaziTarihi": "6 Haziran 2025 Cuma",
      "RamazanBayramNamaziHTarihi": "1 Şevval 1446",
      "RamazanBayramNamaziSaati": "06:54:00",
      "RamazanBayramNamaziTarihi": "30 Mart 2025 Pazar"
    },
    "ilceBilgisi": {
      "CografiKibleAcisi": "64",
      "IlceAdi": "ABUJA",
      "IlceAdiEn": null,
      "IlceID": "15600",
      "KabeyeUzaklik": "3748",
      "KibleAcisi": "66",
      "SehirAdi": "NIJERYA",
      "SehirAdiEn": null,
      "UlkeAdi": "NIJERYA",
      "UlkeAdiEn": null
    }
  },
  {
    "bayramNamazVakti": {
      "KurbanBayramNamaziHTarihi": "10 Zilhicce 1446",
      "KurbanBayramNamaziSaati": "06:42:00",
      "KurbanBayramNamaziTarihi": "6 Haziran 2025 Cuma",
      "RamazanBayramNamaziHTarihi": "1 Şevval 1446",
      "RamazanBayramNamaziSaati": "06:55:00",
      "RamazanBayramNamaziTarihi": "30 Mart 2025 Pazar"
    },
    "ilceBilgisi": {
      "CografiKibleAcisi": "61",
      "IlceAdi": "AKWA",
      "IlceAdiEn": null,
      "IlceID": "15585",
      "KabeyeUzaklik": "3908",
      "KibleAcisi": "64",
      "SehirAdi": "NIJERYA",
      "SehirAdiEn": null,
      "UlkeAdi": "NIJERYA",
      "UlkeAdiEn": null
    }
  },
  {
    "bayramNamazVakti": {
      "KurbanBayramNamaziHTarihi": "10 Zilhicce 1446",
      "KurbanBayramNamaziSaati": "06:47:00",
      "KurbanBayramNamaziTarihi": "6 Haziran 2025 Cuma",
      "RamazanBayramNamaziHTarihi": "1 Şevval 1446",
      "RamazanBayramNamaziSaati": "07:01:00",
      "RamazanBayramNamaziTarihi": "30 Mart 2025 Pazar"
    },
    "ilceBilgisi": {
      "CografiKibleAcisi": "62",
      "IlceAdi": "BENIN CITY",
      "IlceAdiEn": null,
      "IlceID": "15572",
      "KabeyeUzaklik": "4042",
      "KibleAcisi": "65",
      "SehirAdi": "NIJERYA",
      "SehirAdiEn": null,
      "UlkeAdi": "NIJERYA",
      "UlkeAdiEn": null
    }
  },
  {
    "bayramNamazVakti": {
      "KurbanBayramNamaziHTarihi": "10 Zilhicce 1446",
      "KurbanBayramNamaziSaati": "06:39:00",
      "KurbanBayramNamaziTarihi": "6 Haziran 2025 Cuma",
      "RamazanBayramNamaziHTarihi": "1 Şevval 1446",
      "RamazanBayramNamaziSaati": "06:50:00",
      "RamazanBayramNamaziTarihi": "30 Mart 2025 Pazar"
    },
    "ilceBilgisi": {
      "CografiKibleAcisi": "58",
      "IlceAdi": "CALABAR",
      "IlceAdiEn": null,
      "IlceID": "15583",
      "KabeyeUzaklik": "3859",
      "KibleAcisi": "62",
      "SehirAdi": "NIJERYA",
      "SehirAdiEn": null,
      "UlkeAdi": "NIJERYA",
      "UlkeAdiEn": null
    }
  },
  {
    "bayramNamazVakti": {
      "KurbanBayramNamaziHTarihi": "10 Zilhicce 1446",
      "KurbanBayramNamaziSaati": "06:18:00",
      "KurbanBayramNamaziTarihi": "6 Haziran 2025 Cuma",
      "RamazanBayramNamaziHTarihi": "1 Şevval 1446",
      "RamazanBayramNamaziSaati": "06:37:00",
      "RamazanBayramNamaziTarihi": "30 Mart 2025 Pazar"
    },
    "ilceBilgisi": {
      "CografiKibleAcisi": "64",
      "IlceAdi": "DEBA HABE",
      "IlceAdiEn": null,
      "IlceID": "15595",
      "KabeyeUzaklik": "3281",
      "KibleAcisi": "65",
      "SehirAdi": "NIJERYA",
      "SehirAdiEn": null,
      "UlkeAdi": "NIJERYA",
      "UlkeAdiEn": null
    }
  },
  {
    "bayramNamazVakti": {
      "KurbanBayramNamaziHTarihi": "10 Zilhicce 1446",
      "KurbanBayramNamaziSaati": "06:40:00",
      "KurbanBayramNamaziTarihi": "6 Haziran 2025 Cuma",
      "RamazanBayramNamaziHTarihi": "1 Şevval 1446",
      "RamazanBayramNamaziSaati": "06:53:00",
      "RamazanBayramNamaziTarihi": "30 Mart 2025 Pazar"
    },
    "ilceBilgisi": {
      "CografiKibleAcisi": "61",
      "IlceAdi": "ENUGU",
      "IlceAdiEn": null,
      "IlceID": "15584",
      "KabeyeUzaklik": "3854",
      "KibleAcisi": "63",
      "SehirAdi": "NIJERYA",
      "SehirAdiEn": null,
      "UlkeAdi": "NIJERYA",
      "UlkeAdiEn": null
    }
  },
  {
    "bayramNamazVakti": {
      "KurbanBayramNamaziHTarihi": "10 Zilhicce 1446",
      "KurbanBayramNamaziSaati": "06:34:00",
      "KurbanBayramNamaziTarihi": "6 Haziran 2025 Cuma",
      "RamazanBayramNamaziHTarihi": "1 Şevval 1446",
      "RamazanBayramNamaziSaati": "06:55:00",
      "RamazanBayramNamaziTarihi": "30 Mart 2025 Pazar"
    },
    "ilceBilgisi": {
      "CografiKibleAcisi": "69",
      "IlceAdi": "GUSAU",
      "IlceAdiEn": null,
      "IlceID": "15592",
      "KabeyeUzaklik": "3669",
      "KibleAcisi": "71",
      "SehirAdi": "NIJERYA",
      "SehirAdiEn": null,
      "UlkeAdi": "NIJERYA",
      "UlkeAdiEn": null
    }
  },
  {
    "bayramNamazVakti": {
      "KurbanBayramNamaziHTarihi": "10 Zilhicce 1446",
      "KurbanBayramNamaziSaati": "06:53:00",
      "KurbanBayramNamaziTarihi": "6 Haziran 2025 Cuma",
      "RamazanBayramNamaziHTarihi": "1 Şevval 1446",
      "RamazanBayramNamaziSaati": "07:07:00",
      "RamazanBayramNamaziTarihi": "30 Mart 2025 Pazar"
    },
    "ilceBilgisi": {
      "CografiKibleAcisi": "64",
      "IlceAdi": "IBADAN",
      "IlceAdiEn": null,
      "IlceID": "15573",
      "KabeyeUzaklik": "4159",
      "KibleAcisi": "67",
      "SehirAdi": "NIJERYA",
      "SehirAdiEn": null,
      "UlkeAdi": "NIJERYA",
      "UlkeAdiEn": null
    }
  },
  {
    "bayramNamazVakti": {
      "KurbanBayramNamaziHTarihi": "10 Zilhicce 1446",
      "KurbanBayramNamaziSaati": "06:50:00",
      "KurbanBayramNamaziTarihi": "6 Haziran 2025 Cuma",
      "RamazanBayramNamaziHTarihi": "1 Şevval 1446",
      "RamazanBayramNamaziSaati": "07:05:00",
      "RamazanBayramNamaziTarihi": "30 Mart 2025 Pazar"
    },
    "ilceBilgisi": {
      "CografiKibleAcisi": "63",
      "IlceAdi": "IFE",
      "IlceAdiEn": null,
      "IlceID": "15574",
      "KabeyeUzaklik": "4089",
      "KibleAcisi": "67",
      "SehirAdi": "NIJERYA",
      "SehirAdiEn": null,
      "UlkeAdi": "NIJERYA",
      "UlkeAdiEn": null
    }
  },
  {
    "bayramNamazVakti": {
      "KurbanBayramNamaziHTarihi": "10 Zilhicce 1446",
      "KurbanBayramNamaziSaati": "06:51:00",
      "KurbanBayramNamaziTarihi": "6 Haziran 2025 Cuma",
      "RamazanBayramNamaziHTarihi": "1 Şevval 1446",
      "RamazanBayramNamaziSaati": "07:06:00",
      "RamazanBayramNamaziTarihi": "30 Mart 2025 Pazar"
    },
    "ilceBilgisi": {
      "CografiKibleAcisi": "63",
      "IlceAdi": "IKIRE",
      "IlceAdiEn": null,
      "IlceID": "15580",
      "KabeyeUzaklik": "4133",
      "KibleAcisi": "67",
      "SehirAdi": "NIJERYA",
      "SehirAdiEn": null,
      "UlkeAdi": "NIJERYA",
      "UlkeAdiEn": null
    }
  },
  {
    "bayramNamazVakti": {
      "KurbanBayramNamaziHTarihi": "10 Zilhicce 1446",
      "KurbanBayramNamaziSaati": "06:51:00",
      "KurbanBayramNamaziTarihi": "6 Haziran 2025 Cuma",
      "RamazanBayramNamaziHTarihi": "1 Şevval 1446",
      "RamazanBayramNamaziSaati": "07:06:00",
      "RamazanBayramNamaziTarihi": "30 Mart 2025 Pazar"
    },
    "ilceBilgisi": {
      "CografiKibleAcisi": "64",
      "IlceAdi": "IWO",
      "IlceAdiEn": null,
      "IlceID": "15581",
      "KabeyeUzaklik": "4119",
      "KibleAcisi": "67",
      "SehirAdi": "NIJERYA",
      "SehirAdiEn": null,
      "UlkeAdi": "NIJERYA",
      "UlkeAdiEn": null
    }
  },
  {
    "bayramNamazVakti": {
      "KurbanBayramNamaziHTarihi": "10 Zilhicce 1446",
      "KurbanBayramNamaziSaati": "06:33:00",
      "KurbanBayramNamaziTarihi": "6 Haziran 2025 Cuma",
      "RamazanBayramNamaziHTarihi": "1 Şevval 1446",
      "RamazanBayramNamaziSaati": "06:52:00",
      "RamazanBayramNamaziTarihi": "30 Mart 2025 Pazar"
    },
    "ilceBilgisi": {
      "CografiKibleAcisi": "66",
      "IlceAdi": "KADUNA",
      "IlceAdiEn": null,
      "IlceID": "15575",
      "KabeyeUzaklik": "3659",
      "KibleAcisi": "68",
      "SehirAdi": "NIJERYA",
      "SehirAdiEn": null,
      "UlkeAdi": "NIJERYA",
      "UlkeAdiEn": null
    }
  },
  {
    "bayramNamazVakti": {
      "KurbanBayramNamaziHTarihi": "10 Zilhicce 1446",
      "KurbanBayramNamaziSaati": "06:26:00",
      "KurbanBayramNamaziTarihi": "6 Haziran 2025 Cuma",
      "RamazanBayramNamaziHTarihi": "1 Şevval 1446",
      "RamazanBayramNamaziSaati": "06:48:00",
      "RamazanBayramNamaziTarihi": "30 Mart 2025 Pazar"
    },
    "ilceBilgisi": {
      "CografiKibleAcisi": "68",
      "IlceAdi": "KANO",
      "IlceAdiEn": null,
      "IlceID": "15590",
      "KabeyeUzaklik": "3489",
      "KibleAcisi": "69",
      "SehirAdi": "NIJERYA",
      "SehirAdiEn": null,
      "UlkeAdi": "NIJERYA",
      "UlkeAdiEn": null
    }
  },
  {
    "bayramNamazVakti": {
      "KurbanBayramNamaziHTarihi": "10 Zilhicce 1446",
      "KurbanBayramNamaziSaati": "06:28:00",
      "KurbanBayramNamaziTarihi": "6 Haziran 2025 Cuma",
      "RamazanBayramNamaziHTarihi": "1 Şevval 1446",
      "RamazanBayramNamaziSaati": "06:51:00",
      "RamazanBayramNamaziTarihi": "30 Mart 2025 Pazar"
    },
    "ilceBilgisi": {
      "CografiKibleAcisi": "70",
      "IlceAdi": "KATSINA",
      "IlceAdiEn": null,
      "IlceID": "15591",
      "KabeyeUzaklik": "3541",
      "KibleAcisi": "71",
      "SehirAdi": "NIJERYA",
      "SehirAdiEn": null,
      "UlkeAdi": "NIJERYA",
      "UlkeAdiEn": null
    }
  },
  {
    "bayramNamazVakti": {
      "KurbanBayramNamaziHTarihi": "10 Zilhicce 1446",
      "KurbanBayramNamaziSaati": "06:32:00",
      "KurbanBayramNamaziTarihi": "6 Haziran 2025 Cuma",
      "RamazanBayramNamaziHTarihi": "1 Şevval 1446",
      "RamazanBayramNamaziSaati": "06:48:00",
      "RamazanBayramNamaziTarihi": "30 Mart 2025 Pazar"
    },
    "ilceBilgisi": {
      "CografiKibleAcisi": "63",
      "IlceAdi": "LAFIA",
      "IlceAdiEn": null,
      "IlceID": "15588",
      "KabeyeUzaklik": "3648",
      "KibleAcisi": "65",
      "SehirAdi": "NIJERYA",
      "SehirAdiEn": null,
      "UlkeAdi": "NIJERYA",
      "UlkeAdiEn": null
    }
  },
  {
    "bayramNamazVakti": {
      "KurbanBayramNamaziHTarihi": "10 Zilhicce 1446",
      "KurbanBayramNamaziSaati": "06:56:00",
      "KurbanBayramNamaziTarihi": "6 Haziran 2025 Cuma",
      "RamazanBayramNamaziHTarihi": "1 Şevval 1446",
      "RamazanBayramNamaziSaati": "07:09:00",
      "RamazanBayramNamaziTarihi": "30 Mart 2025 Pazar"
    },
    "ilceBilgisi": {
      "CografiKibleAcisi": "63",
      "IlceAdi": "LAGOS",
      "IlceAdiEn": null,
      "IlceID": "15601",
      "KabeyeUzaklik": "4255",
      "KibleAcisi": "66",
      "SehirAdi": "NIJERYA",
      "SehirAdiEn": null,
      "UlkeAdi": "NIJERYA",
      "UlkeAdiEn": null
    }
  },
  {
    "bayramNamazVakti": {
      "KurbanBayramNamaziHTarihi": "10 Zilhicce 1446",
      "KurbanBayramNamaziSaati": "06:08:00",
      "KurbanBayramNamaziTarihi": "6 Haziran 2025 Cuma",
      "RamazanBayramNamaziHTarihi": "1 Şevval 1446",
      "RamazanBayramNamaziSaati": "06:29:00",
      "RamazanBayramNamaziTarihi": "30 Mart 2025 Pazar"
    },
    "ilceBilgisi": {
      "CografiKibleAcisi": "65",
      "IlceAdi": "MAIDUGURI",
      "IlceAdiEn": null,
      "IlceID": "15594",
      "KabeyeUzaklik": "3029",
      "KibleAcisi": "66",
      "SehirAdi": "NIJERYA",
      "SehirAdiEn": null,
      "UlkeAdi": "NIJERYA",
      "UlkeAdiEn": null
    }
  },
  {
    "bayramNamazVakti": {
      "KurbanBayramNamaziHTarihi": "10 Zilhicce 1446",
      "KurbanBayramNamaziSaati": "06:33:00",
      "KurbanBayramNamaziTarihi": "6 Haziran 2025 Cuma",
      "RamazanBayramNamaziHTarihi": "1 Şevval 1446",
      "RamazanBayramNamaziSaati": "06:49:00",
      "RamazanBayramNamaziTarihi": "30 Mart 2025 Pazar"
    },
    "ilceBilgisi": {
      "CografiKibleAcisi": "62",
      "IlceAdi": "MAKURDI",
      "IlceAdiEn": null,
      "IlceID": "15587",
      "KabeyeUzaklik": "3685",
      "KibleAcisi": "64",
      "SehirAdi": "NIJERYA",
      "SehirAdiEn": null,
      "UlkeAdi": "NIJERYA",
      "UlkeAdiEn": null
    }
  },
  {
    "bayramNamazVakti": {
      "KurbanBayramNamaziHTarihi": "10 Zilhicce 1446",
      "KurbanBayramNamaziSaati": "06:38:00",
      "KurbanBayramNamaziTarihi": "6 Haziran 2025 Cuma",
      "RamazanBayramNamaziHTarihi": "1 Şevval 1446",
      "RamazanBayramNamaziSaati": "06:56:00",
      "RamazanBayramNamaziTarihi": "30 Mart 2025 Pazar"
    },
    "ilceBilgisi": {
      "CografiKibleAcisi": "65",
      "IlceAdi": "MINNA",
      "IlceAdiEn": null,
      "IlceID": "15597",
      "KabeyeUzaklik": "3790",
      "KibleAcisi": "68",
      "SehirAdi": "NIJERYA",
      "SehirAdiEn": null,
      "UlkeAdi": "NIJERYA",
      "UlkeAdiEn": null
    }
  },
  {
    "bayramNamazVakti": {
      "KurbanBayramNamaziHTarihi": "10 Zilhicce 1446",
      "KurbanBayramNamaziSaati": "06:43:00",
      "KurbanBayramNamaziTarihi": "6 Haziran 2025 Cuma",
      "RamazanBayramNamaziHTarihi": "1 Şevval 1446",
      "RamazanBayramNamaziSaati": "06:56:00",
      "RamazanBayramNamaziTarihi": "30 Mart 2025 Pazar"
    },
    "ilceBilgisi": {
      "CografiKibleAcisi": "61",
      "IlceAdi": "ONITSHA",
      "IlceAdiEn": null,
      "IlceID": "15586",
      "KabeyeUzaklik": "3939",
      "KibleAcisi": "64",
      "SehirAdi": "NIJERYA",
      "SehirAdiEn": null,
      "UlkeAdi": "NIJERYA",
      "UlkeAdiEn": null
    }
  },
  {
    "bayramNamazVakti": {
      "KurbanBayramNamaziHTarihi": "10 Zilhicce 1446",
      "KurbanBayramNamaziSaati": "06:49:00",
      "KurbanBayramNamaziTarihi": "6 Haziran 2025 Cuma",
      "RamazanBayramNamaziHTarihi": "1 Şevval 1446",
      "RamazanBayramNamaziSaati": "07:04:00",
      "RamazanBayramNamaziTarihi": "30 Mart 2025 Pazar"
    },
    "ilceBilgisi": {
      "CografiKibleAcisi": "64",
      "IlceAdi": "OSHOGBO",
      "IlceAdiEn": null,
      "IlceID": "15576",
      "KabeyeUzaklik": "4075",
      "KibleAcisi": "67",
      "SehirAdi": "NIJERYA",
      "SehirAdiEn": null,
      "UlkeAdi": "NIJERYA",
      "UlkeAdiEn": null
    }
  },
  {
    "bayramNamazVakti": {
      "KurbanBayramNamaziHTarihi": "10 Zilhicce 1446",
      "KurbanBayramNamaziSaati": "06:44:00",
      "KurbanBayramNamaziTarihi": "6 Haziran 2025 Cuma",
      "RamazanBayramNamaziHTarihi": "1 Şevval 1446",
      "RamazanBayramNamaziSaati": "06:55:00",
      "RamazanBayramNamaziTarihi": "30 Mart 2025 Pazar"
    },
    "ilceBilgisi": {
      "CografiKibleAcisi": "59",
      "IlceAdi": "PORT HARCOURT",
      "IlceAdiEn": null,
      "IlceID": "15577",
      "KabeyeUzaklik": "3993",
      "KibleAcisi": "62",
      "SehirAdi": "NIJERYA",
      "SehirAdiEn": null,
      "UlkeAdi": "NIJERYA",
      "UlkeAdiEn": null
    }
  },
  {
    "bayramNamazVakti": {
      "KurbanBayramNamaziHTarihi": "10 Zilhicce 1446",
      "KurbanBayramNamaziSaati": "06:52:00",
      "KurbanBayramNamaziTarihi": "6 Haziran 2025 Cuma",
      "RamazanBayramNamaziHTarihi": "1 Şevval 1446",
      "RamazanBayramNamaziSaati": "07:09:00",
      "RamazanBayramNamaziTarihi": "30 Mart 2025 Pazar"
    },
    "ilceBilgisi": {
      "CografiKibleAcisi": "65",
      "IlceAdi": "SAKI",
      "IlceAdiEn": null,
      "IlceID": "15596",
      "KabeyeUzaklik": "4148",
      "KibleAcisi": "69",
      "SehirAdi": "NIJERYA",
      "SehirAdiEn": null,
      "UlkeAdi": "NIJERYA",
      "UlkeAdiEn": null
    }
  },
  {
    "bayramNamazVakti": {
      "KurbanBayramNamaziHTarihi": "10 Zilhicce 1446",
      "KurbanBayramNamaziSaati": "06:48:00",
      "KurbanBayramNamaziTarihi": "6 Haziran 2025 Cuma",
      "RamazanBayramNamaziHTarihi": "1 Şevval 1446",
      "RamazanBayramNamaziSaati": "07:00:00",
      "RamazanBayramNamaziTarihi": "30 Mart 2025 Pazar"
    },
    "ilceBilgisi": {
      "CografiKibleAcisi": "61",
      "IlceAdi": "SAPELE",
      "IlceAdiEn": null,
      "IlceID": "15578",
      "KabeyeUzaklik": "4060",
      "KibleAcisi": "64",
      "SehirAdi": "NIJERYA",
      "SehirAdiEn": null,
      "UlkeAdi": "NIJERYA",
      "UlkeAdiEn": null
    }
  },
  {
    "bayramNamazVakti": {
      "KurbanBayramNamaziHTarihi": "10 Zilhicce 1446",
      "KurbanBayramNamaziSaati": "06:38:00",
      "KurbanBayramNamaziTarihi": "6 Haziran 2025 Cuma",
      "RamazanBayramNamaziHTarihi": "1 Şevval 1446",
      "RamazanBayramNamaziSaati": "07:01:00",
      "RamazanBayramNamaziTarihi": "30 Mart 2025 Pazar"
    },
    "ilceBilgisi": {
      "CografiKibleAcisi": "70",
      "IlceAdi": "SOKOTO",
      "IlceAdiEn": null,
      "IlceID": "15593",
      "KabeyeUzaklik": "3780",
      "KibleAcisi": "72",
      "SehirAdi": "NIJERYA",
      "SehirAdiEn": null,
      "UlkeAdi": "NIJERYA",
      "UlkeAdiEn": null
    }
  },
  {
    "bayramNamazVakti": {
      "KurbanBayramNamaziHTarihi": "10 Zilhicce 1446",
      "KurbanBayramNamaziSaati": "06:48:00",
      "KurbanBayramNamaziTarihi": "6 Haziran 2025 Cuma",
      "RamazanBayramNamaziHTarihi": "1 Şevval 1446",
      "RamazanBayramNamaziSaati": "07:00:00",
      "RamazanBayramNamaziTarihi": "30 Mart 2025 Pazar"
    },
    "ilceBilgisi": {
      "CografiKibleAcisi": "60",
      "IlceAdi": "WARRI",
      "IlceAdiEn": null,
      "IlceID": "15579",
      "KabeyeUzaklik": "4073",
      "KibleAcisi": "64",
      "SehirAdi": "NIJERYA",
      "SehirAdiEn": null,
      "UlkeAdi": "NIJERYA",
      "UlkeAdiEn": null
    }
  },
  {
    "bayramNamazVakti": {
      "KurbanBayramNamaziHTarihi": "10 Zilhicce 1446",
      "KurbanBayramNamaziSaati": "06:31:00",
      "KurbanBayramNamaziTarihi": "6 Haziran 2025 Cuma",
      "RamazanBayramNamaziHTarihi": "1 Şevval 1446",
      "RamazanBayramNamaziSaati": "06:51:00",
      "RamazanBayramNamaziTarihi": "30 Mart 2025 Pazar"
    },
    "ilceBilgisi": {
      "CografiKibleAcisi": "67",
      "IlceAdi": "ZARIA",
      "IlceAdiEn": null,
      "IlceID": "15589",
      "KabeyeUzaklik": "3607",
      "KibleAcisi": "69",
      "SehirAdi": "NIJERYA",
      "SehirAdiEn": null,
      "UlkeAdi": "NIJERYA",
      "UlkeAdiEn": null
    }
  }
]