[
  {
    "bayramNamazVakti": {
      "KurbanBayramNamaziHTarihi": "10 Zilhicce 1446",
      "KurbanBayramNamaziSaati": "05:34:00",
      "KurbanBayramNamaziTarihi": "6 Haziran 2025 Cuma",
      "RamazanBayramNamaziHTarihi": "1 Şevval 1446",
      "RamazanBayramNamaziSaati": "06:57:00",
      "RamazanBayramNamaziTarihi": "30 Mart 2025 Pazar"
    },
    "ilceBilgisi": {
      "CografiKibleAcisi": "61",
      "IlceAdi": "AUGUSTA",
      "IlceAdiEn": null,
      "IlceID": "8797",
      "KabeyeUzaklik": "9809",
      "KibleAcisi": "77",
      "SehirAdi": "MAINE",
      "SehirAdiEn": null,
      "UlkeAdi": "ABD",
      "UlkeAdiEn": null
    }
  },
  {
    "bayramNamazVakti": {
      "KurbanBayramNamaziHTarihi": "10 Zilhicce 1446",
      "KurbanBayramNamaziSaati": "05:31:00",
      "KurbanBayramNamaziTarihi": "6 Haziran 2025 Cuma",
      "RamazanBayramNamaziHTarihi": "1 Şevval 1446",
      "RamazanBayramNamaziSaati": "06:54:00",
      "RamazanBayramNamaziTarihi": "30 Mart 2025 Pazar"
    },
    "ilceBilgisi": {
      "CografiKibleAcisi": "61",
      "IlceAdi": "CAMDEN",
      "IlceAdiEn": null,
      "IlceID": "8798",
      "KabeyeUzaklik": "9764",
      "KibleAcisi": "78",
      "SehirAdi": "MAINE",
      "SehirAdiEn": null,
      "UlkeAdi": "ABD",
      "UlkeAdiEn": null
    }
  }
]