[
  {
    "bayramNamazVakti": {
      "KurbanBayramNamaziHTarihi": "10 Zilhicce 1446",
      "KurbanBayramNamaziSaati": "05:33:00",
      "KurbanBayramNamaziTarihi": "6 Haziran 2025 Cuma",
      "RamazanBayramNamaziHTarihi": "1 Şevval 1446",
      "RamazanBayramNamaziSaati": "06:42:00",
      "RamazanBayramNamaziTarihi": "30 Mart 2025 Pazar"
    },
    "ilceBilgisi": {
      "CografiKibleAcisi": "177",
      "IlceAdi": "ÇEMİŞGEZEK",
      "IlceAdiEn": null,
      "IlceID": "9908",
      "KabeyeUzaklik": "1962",
      "KibleAcisi": "172",
      "SehirAdi": "TUNCELİ",
      "SehirAdiEn": null,
      "UlkeAdi": "TÜRKİYE",
      "UlkeAdiEn": null
    }
  },
  {
    "bayramNamazVakti": {
      "KurbanBayramNamaziHTarihi": "10 Zilhicce 1446",
      "KurbanBayramNamaziSaati": "05:32:00",
      "KurbanBayramNamaziTarihi": "6 Haziran 2025 Cuma",
      "RamazanBayramNamaziHTarihi": "1 Şevval 1446",
      "RamazanBayramNamaziSaati": "06:41:00",
      "RamazanBayramNamaziTarihi": "30 Mart 2025 Pazar"
    },
    "ilceBilgisi": {
      "CografiKibleAcisi": "178",
      "IlceAdi": "HOZAT",
      "IlceAdiEn": null,
      "IlceID": "9909",
      "KabeyeUzaklik": "1966",
      "KibleAcisi": "173",
      "SehirAdi": "TUNCELİ",
      "SehirAdiEn": null,
      "UlkeAdi": "TÜRKİYE",
      "UlkeAdiEn": null
    }
  },
  {
    "bayramNamazVakti": {
      "KurbanBayramNamaziHTarihi": "10 Zilhicce 1446",
      "KurbanBayramNamaziSaati": "05:29:00",
      "KurbanBayramNamaziTarihi": "6 Haziran 2025 Cuma",
      "RamazanBayramNamaziHTarihi": "1 Şevval 1446",
      "RamazanBayramNamaziSaati": "06:39:00",
      "RamazanBayramNamaziTarihi": "30 Mart 2025 Pazar"
    },
    "ilceBilgisi": {
      "CografiKibleAcisi": "179",
      "IlceAdi": "NAZİMİYE",
      "IlceAdiEn": null,
      "IlceID": "9910",
      "KabeyeUzaklik": "1974",
      "KibleAcisi": "175",
      "SehirAdi": "TUNCELİ",
      "SehirAdiEn": null,
      "UlkeAdi": "TÜRKİYE",
      "UlkeAdiEn": null
    }
  },
  {
    "bayramNamazVakti": {
      "KurbanBayramNamaziHTarihi": "10 Zilhicce 1446",
      "KurbanBayramNamaziSaati": "05:31:00",
      "KurbanBayramNamaziTarihi": "6 Haziran 2025 Cuma",
      "RamazanBayramNamaziHTarihi": "1 Şevval 1446",
      "RamazanBayramNamaziSaati": "06:41:00",
      "RamazanBayramNamaziTarihi": "30 Mart 2025 Pazar"
    },
    "ilceBilgisi": {
      "CografiKibleAcisi": "178",
      "IlceAdi": "OVACIK",
      "IlceAdiEn": null,
      "IlceID": "9911",
      "KabeyeUzaklik": "1994",
      "KibleAcisi": "173",
      "SehirAdi": "TUNCELİ",
      "SehirAdiEn": null,
      "UlkeAdi": "TÜRKİYE",
      "UlkeAdiEn": null
    }
  },
  {
    "bayramNamazVakti": {
      "KurbanBayramNamaziHTarihi": "10 Zilhicce 1446",
      "KurbanBayramNamaziSaati": "05:32:00",
      "KurbanBayramNamaziTarihi": "6 Haziran 2025 Cuma",
      "RamazanBayramNamaziHTarihi": "1 Şevval 1446",
      "RamazanBayramNamaziSaati": "06:41:00",
      "RamazanBayramNamaziTarihi": "30 Mart 2025 Pazar"
    },
    "ilceBilgisi": {
      "CografiKibleAcisi": "178",
      "IlceAdi": "PERTEK",
      "IlceAdiEn": null,
      "IlceID": "9912",
      "KabeyeUzaklik": "1940",
      "KibleAcisi": "173",
      "SehirAdi": "TUNCELİ",
      "SehirAdiEn": null,
      "UlkeAdi": "TÜRKİYE",
      "UlkeAdiEn": null
    }
  },
  {
    "bayramNamazVakti": {
      "KurbanBayramNamaziHTarihi": "10 Zilhicce 1446",
      "KurbanBayramNamaziSaati": "05:28:00",
      "KurbanBayramNamaziTarihi": "6 Haziran 2025 Cuma",
      "RamazanBayramNamaziHTarihi": "1 Şevval 1446",
      "RamazanBayramNamaziSaati": "06:38:00",
      "RamazanBayramNamaziTarihi": "30 Mart 2025 Pazar"
    },
    "ilceBilgisi": {
      "CografiKibleAcisi": "180",
      "IlceAdi": "PÜLÜMÜR",
      "IlceAdiEn": null,
      "IlceID": "9913",
      "KabeyeUzaklik": "2008",
      "KibleAcisi": "175",
      "SehirAdi": "TUNCELİ",
      "SehirAdiEn": null,
      "UlkeAdi": "TÜRKİYE",
      "UlkeAdiEn": null
    }
  },
  {
    "bayramNamazVakti": {
      "KurbanBayramNamaziHTarihi": "10 Zilhicce 1446",
      "KurbanBayramNamaziSaati": "05:30:00",
      "KurbanBayramNamaziTarihi": "6 Haziran 2025 Cuma",
      "RamazanBayramNamaziHTarihi": "1 Şevval 1446",
      "RamazanBayramNamaziSaati": "06:40:00",
      "RamazanBayramNamaziTarihi": "30 Mart 2025 Pazar"
    },
    "ilceBilgisi": {
      "CografiKibleAcisi": "179",
      "IlceAdi": "TUNCELİ",
      "IlceAdiEn": null,
      "IlceID": "9914",
      "KabeyeUzaklik": "1965",
      "KibleAcisi": "174",
      "SehirAdi": "TUNCELİ",
      "SehirAdiEn": null,
      "UlkeAdi": "TÜRKİYE",
      "UlkeAdiEn": null
    }
  }
]