[
  {
    "bayramNamazVakti": {
      "KurbanBayramNamaziHTarihi": "10 Zilhicce 1446",
      "KurbanBayramNamaziSaati": "05:34:00",
      "KurbanBayramNamaziTarihi": "6 Haziran 2025 Cuma",
      "RamazanBayramNamaziHTarihi": "1 Şevval 1446",
      "RamazanBayramNamaziSaati": "06:43:00",
      "RamazanBayramNamaziTarihi": "30 Mart 2025 Pazar"
    },
    "ilceBilgisi": {
      "CografiKibleAcisi": "176",
      "IlceAdi": "AĞIN",
      "IlceAdiEn": null,
      "IlceID": "9428",
      "KabeyeUzaklik": "1950",
      "KibleAcisi": "172",
      "SehirAdi": "ELAZIĞ",
      "SehirAdiEn": null,
      "UlkeAdi": "TÜRKİYE",
      "UlkeAdiEn": null
    }
  },
  {
    "bayramNamazVakti": {
      "KurbanBayramNamaziHTarihi": "10 Zilhicce 1446",
      "KurbanBayramNamaziSaati": "05:31:00",
      "KurbanBayramNamaziTarihi": "6 Haziran 2025 Cuma",
      "RamazanBayramNamaziHTarihi": "1 Şevval 1446",
      "RamazanBayramNamaziSaati": "06:39:00",
      "RamazanBayramNamaziTarihi": "30 Mart 2025 Pazar"
    },
    "ilceBilgisi": {
      "CografiKibleAcisi": "180",
      "IlceAdi": "ALACAKAYA",
      "IlceAdiEn": null,
      "IlceID": "9429",
      "KabeyeUzaklik": "1894",
      "KibleAcisi": "175",
      "SehirAdi": "ELAZIĞ",
      "SehirAdiEn": null,
      "UlkeAdi": "TÜRKİYE",
      "UlkeAdiEn": null
    }
  },
  {
    "bayramNamazVakti": {
      "KurbanBayramNamaziHTarihi": "10 Zilhicce 1446",
      "KurbanBayramNamaziSaati": "05:29:00",
      "KurbanBayramNamaziTarihi": "6 Haziran 2025 Cuma",
      "RamazanBayramNamaziHTarihi": "1 Şevval 1446",
      "RamazanBayramNamaziSaati": "06:38:00",
      "RamazanBayramNamaziTarihi": "30 Mart 2025 Pazar"
    },
    "ilceBilgisi": {
      "CografiKibleAcisi": "180",
      "IlceAdi": "ARICAK",
      "IlceAdiEn": null,
      "IlceID": "9430",
      "KabeyeUzaklik": "1906",
      "KibleAcisi": "176",
      "SehirAdi": "ELAZIĞ",
      "SehirAdiEn": null,
      "UlkeAdi": "TÜRKİYE",
      "UlkeAdiEn": null
    }
  },
  {
    "bayramNamazVakti": {
      "KurbanBayramNamaziHTarihi": "10 Zilhicce 1446",
      "KurbanBayramNamaziSaati": "05:34:00",
      "KurbanBayramNamaziTarihi": "6 Haziran 2025 Cuma",
      "RamazanBayramNamaziHTarihi": "1 Şevval 1446",
      "RamazanBayramNamaziSaati": "06:43:00",
      "RamazanBayramNamaziTarihi": "30 Mart 2025 Pazar"
    },
    "ilceBilgisi": {
      "CografiKibleAcisi": "176",
      "IlceAdi": "BASKİL",
      "IlceAdiEn": null,
      "IlceID": "9431",
      "KabeyeUzaklik": "1908",
      "KibleAcisi": "172",
      "SehirAdi": "ELAZIĞ",
      "SehirAdiEn": null,
      "UlkeAdi": "TÜRKİYE",
      "UlkeAdiEn": null
    }
  },
  {
    "bayramNamazVakti": {
      "KurbanBayramNamaziHTarihi": "10 Zilhicce 1446",
      "KurbanBayramNamaziSaati": "05:33:00",
      "KurbanBayramNamaziTarihi": "6 Haziran 2025 Cuma",
      "RamazanBayramNamaziHTarihi": "1 Şevval 1446",
      "RamazanBayramNamaziSaati": "06:41:00",
      "RamazanBayramNamaziTarihi": "30 Mart 2025 Pazar"
    },
    "ilceBilgisi": {
      "CografiKibleAcisi": "178",
      "IlceAdi": "ELAZIĞ",
      "IlceAdiEn": null,
      "IlceID": "9432",
      "KabeyeUzaklik": "1918",
      "KibleAcisi": "173",
      "SehirAdi": "ELAZIĞ",
      "SehirAdiEn": null,
      "UlkeAdi": "TÜRKİYE",
      "UlkeAdiEn": null
    }
  },
  {
    "bayramNamazVakti": {
      "KurbanBayramNamaziHTarihi": "10 Zilhicce 1446",
      "KurbanBayramNamaziSaati": "05:29:00",
      "KurbanBayramNamaziTarihi": "6 Haziran 2025 Cuma",
      "RamazanBayramNamaziHTarihi": "1 Şevval 1446",
      "RamazanBayramNamaziSaati": "06:38:00",
      "RamazanBayramNamaziTarihi": "30 Mart 2025 Pazar"
    },
    "ilceBilgisi": {
      "CografiKibleAcisi": "180",
      "IlceAdi": "KARAKOÇAN",
      "IlceAdiEn": null,
      "IlceID": "9433",
      "KabeyeUzaklik": "1949",
      "KibleAcisi": "176",
      "SehirAdi": "ELAZIĞ",
      "SehirAdiEn": null,
      "UlkeAdi": "TÜRKİYE",
      "UlkeAdiEn": null
    }
  },
  {
    "bayramNamazVakti": {
      "KurbanBayramNamaziHTarihi": "10 Zilhicce 1446",
      "KurbanBayramNamaziSaati": "05:34:00",
      "KurbanBayramNamaziTarihi": "6 Haziran 2025 Cuma",
      "RamazanBayramNamaziHTarihi": "1 Şevval 1446",
      "RamazanBayramNamaziSaati": "06:43:00",
      "RamazanBayramNamaziTarihi": "30 Mart 2025 Pazar"
    },
    "ilceBilgisi": {
      "CografiKibleAcisi": "176",
      "IlceAdi": "KEBAN",
      "IlceAdiEn": null,
      "IlceID": "9434",
      "KabeyeUzaklik": "1934",
      "KibleAcisi": "172",
      "SehirAdi": "ELAZIĞ",
      "SehirAdiEn": null,
      "UlkeAdi": "TÜRKİYE",
      "UlkeAdiEn": null
    }
  },
  {
    "bayramNamazVakti": {
      "KurbanBayramNamaziHTarihi": "10 Zilhicce 1446",
      "KurbanBayramNamaziSaati": "05:30:00",
      "KurbanBayramNamaziTarihi": "6 Haziran 2025 Cuma",
      "RamazanBayramNamaziHTarihi": "1 Şevval 1446",
      "RamazanBayramNamaziSaati": "06:39:00",
      "RamazanBayramNamaziTarihi": "30 Mart 2025 Pazar"
    },
    "ilceBilgisi": {
      "CografiKibleAcisi": "180",
      "IlceAdi": "KOVANCILAR",
      "IlceAdiEn": null,
      "IlceID": "9435",
      "KabeyeUzaklik": "1923",
      "KibleAcisi": "175",
      "SehirAdi": "ELAZIĞ",
      "SehirAdiEn": null,
      "UlkeAdi": "TÜRKİYE",
      "UlkeAdiEn": null
    }
  },
  {
    "bayramNamazVakti": {
      "KurbanBayramNamaziHTarihi": "10 Zilhicce 1446",
      "KurbanBayramNamaziSaati": "05:31:00",
      "KurbanBayramNamaziTarihi": "6 Haziran 2025 Cuma",
      "RamazanBayramNamaziHTarihi": "1 Şevval 1446",
      "RamazanBayramNamaziSaati": "06:39:00",
      "RamazanBayramNamaziTarihi": "30 Mart 2025 Pazar"
    },
    "ilceBilgisi": {
      "CografiKibleAcisi": "179",
      "IlceAdi": "MADEN",
      "IlceAdiEn": null,
      "IlceID": "9436",
      "KabeyeUzaklik": "1886",
      "KibleAcisi": "175",
      "SehirAdi": "ELAZIĞ",
      "SehirAdiEn": null,
      "UlkeAdi": "TÜRKİYE",
      "UlkeAdiEn": null
    }
  },
  {
    "bayramNamazVakti": {
      "KurbanBayramNamaziHTarihi": "10 Zilhicce 1446",
      "KurbanBayramNamaziSaati": "05:30:00",
      "KurbanBayramNamaziTarihi": "6 Haziran 2025 Cuma",
      "RamazanBayramNamaziHTarihi": "1 Şevval 1446",
      "RamazanBayramNamaziSaati": "06:38:00",
      "RamazanBayramNamaziTarihi": "30 Mart 2025 Pazar"
    },
    "ilceBilgisi": {
      "CografiKibleAcisi": "180",
      "IlceAdi": "PALU",
      "IlceAdiEn": null,
      "IlceID": "9437",
      "KabeyeUzaklik": "1920",
      "KibleAcisi": "175",
      "SehirAdi": "ELAZIĞ",
      "SehirAdiEn": null,
      "UlkeAdi": "TÜRKİYE",
      "UlkeAdiEn": null
    }
  },
  {
    "bayramNamazVakti": {
      "KurbanBayramNamaziHTarihi": "10 Zilhicce 1446",
      "KurbanBayramNamaziSaati": "05:33:00",
      "KurbanBayramNamaziTarihi": "6 Haziran 2025 Cuma",
      "RamazanBayramNamaziHTarihi": "1 Şevval 1446",
      "RamazanBayramNamaziSaati": "06:41:00",
      "RamazanBayramNamaziTarihi": "30 Mart 2025 Pazar"
    },
    "ilceBilgisi": {
      "CografiKibleAcisi": "178",
      "IlceAdi": "SİVRİCE",
      "IlceAdiEn": null,
      "IlceID": "9438",
      "KabeyeUzaklik": "1892",
      "KibleAcisi": "173",
      "SehirAdi": "ELAZIĞ",
      "SehirAdiEn": null,
      "UlkeAdi": "TÜRKİYE",
      "UlkeAdiEn": null
    }
  }
]