[
  {
    "bayramNamazVakti": {
      "KurbanBayramNamaziHTarihi": "10 Zilhicce 1446",
      "KurbanBayramNamaziSaati": "05:43:00",
      "KurbanBayramNamaziTarihi": "6 Haziran 2025 Cuma",
      "RamazanBayramNamaziHTarihi": "1 Şevval 1446",
      "RamazanBayramNamaziSaati": "07:00:00",
      "RamazanBayramNamaziTarihi": "30 Mart 2025 Pazar"
    },
    "ilceBilgisi": {
      "CografiKibleAcisi": "166",
      "IlceAdi": "AYANCIK",
      "IlceAdiEn": null,
      "IlceID": "9840",
      "KabeyeUzaklik": "2333",
      "KibleAcisi": "161",
      "SehirAdi": "SİNOP",
      "SehirAdiEn": null,
      "UlkeAdi": "TÜRKİYE",
      "UlkeAdiEn": null
    }
  },
  {
    "bayramNamazVakti": {
      "KurbanBayramNamaziHTarihi": "10 Zilhicce 1446",
      "KurbanBayramNamaziSaati": "05:43:00",
      "KurbanBayramNamaziTarihi": "6 Haziran 2025 Cuma",
      "RamazanBayramNamaziHTarihi": "1 Şevval 1446",
      "RamazanBayramNamaziSaati": "06:59:00",
      "RamazanBayramNamaziTarihi": "30 Mart 2025 Pazar"
    },
    "ilceBilgisi": {
      "CografiKibleAcisi": "166",
      "IlceAdi": "BOYABAT",
      "IlceAdiEn": null,
      "IlceID": "9841",
      "KabeyeUzaklik": "2278",
      "KibleAcisi": "161",
      "SehirAdi": "SİNOP",
      "SehirAdiEn": null,
      "UlkeAdi": "TÜRKİYE",
      "UlkeAdiEn": null
    }
  },
  {
    "bayramNamazVakti": {
      "KurbanBayramNamaziHTarihi": "10 Zilhicce 1446",
      "KurbanBayramNamaziSaati": "05:41:00",
      "KurbanBayramNamaziTarihi": "6 Haziran 2025 Cuma",
      "RamazanBayramNamaziHTarihi": "1 Şevval 1446",
      "RamazanBayramNamaziSaati": "06:57:00",
      "RamazanBayramNamaziTarihi": "30 Mart 2025 Pazar"
    },
    "ilceBilgisi": {
      "CografiKibleAcisi": "167",
      "IlceAdi": "DİKMEN",
      "IlceAdiEn": null,
      "IlceID": "9842",
      "KabeyeUzaklik": "2289",
      "KibleAcisi": "163",
      "SehirAdi": "SİNOP",
      "SehirAdiEn": null,
      "UlkeAdi": "TÜRKİYE",
      "UlkeAdiEn": null
    }
  },
  {
    "bayramNamazVakti": {
      "KurbanBayramNamaziHTarihi": "10 Zilhicce 1446",
      "KurbanBayramNamaziSaati": "05:42:00",
      "KurbanBayramNamaziTarihi": "6 Haziran 2025 Cuma",
      "RamazanBayramNamaziHTarihi": "1 Şevval 1446",
      "RamazanBayramNamaziSaati": "06:58:00",
      "RamazanBayramNamaziTarihi": "30 Mart 2025 Pazar"
    },
    "ilceBilgisi": {
      "CografiKibleAcisi": "167",
      "IlceAdi": "DURAĞAN",
      "IlceAdiEn": null,
      "IlceID": "9843",
      "KabeyeUzaklik": "2267",
      "KibleAcisi": "162",
      "SehirAdi": "SİNOP",
      "SehirAdiEn": null,
      "UlkeAdi": "TÜRKİYE",
      "UlkeAdiEn": null
    }
  },
  {
    "bayramNamazVakti": {
      "KurbanBayramNamaziHTarihi": "10 Zilhicce 1446",
      "KurbanBayramNamaziSaati": "05:42:00",
      "KurbanBayramNamaziTarihi": "6 Haziran 2025 Cuma",
      "RamazanBayramNamaziHTarihi": "1 Şevval 1446",
      "RamazanBayramNamaziSaati": "06:58:00",
      "RamazanBayramNamaziTarihi": "30 Mart 2025 Pazar"
    },
    "ilceBilgisi": {
      "CografiKibleAcisi": "167",
      "IlceAdi": "ERFELEK",
      "IlceAdiEn": null,
      "IlceID": "9844",
      "KabeyeUzaklik": "2320",
      "KibleAcisi": "162",
      "SehirAdi": "SİNOP",
      "SehirAdiEn": null,
      "UlkeAdi": "TÜRKİYE",
      "UlkeAdiEn": null
    }
  },
  {
    "bayramNamazVakti": {
      "KurbanBayramNamaziHTarihi": "10 Zilhicce 1446",
      "KurbanBayramNamaziSaati": "05:41:00",
      "KurbanBayramNamaziTarihi": "6 Haziran 2025 Cuma",
      "RamazanBayramNamaziHTarihi": "1 Şevval 1446",
      "RamazanBayramNamaziSaati": "06:57:00",
      "RamazanBayramNamaziTarihi": "30 Mart 2025 Pazar"
    },
    "ilceBilgisi": {
      "CografiKibleAcisi": "167",
      "IlceAdi": "GERZE",
      "IlceAdiEn": null,
      "IlceID": "9845",
      "KabeyeUzaklik": "2307",
      "KibleAcisi": "162",
      "SehirAdi": "SİNOP",
      "SehirAdiEn": null,
      "UlkeAdi": "TÜRKİYE",
      "UlkeAdiEn": null
    }
  },
  {
    "bayramNamazVakti": {
      "KurbanBayramNamaziHTarihi": "10 Zilhicce 1446",
      "KurbanBayramNamaziSaati": "05:43:00",
      "KurbanBayramNamaziTarihi": "6 Haziran 2025 Cuma",
      "RamazanBayramNamaziHTarihi": "1 Şevval 1446",
      "RamazanBayramNamaziSaati": "06:59:00",
      "RamazanBayramNamaziTarihi": "30 Mart 2025 Pazar"
    },
    "ilceBilgisi": {
      "CografiKibleAcisi": "166",
      "IlceAdi": "SARAYDÜZÜ",
      "IlceAdiEn": null,
      "IlceID": "9846",
      "KabeyeUzaklik": "2262",
      "KibleAcisi": "161",
      "SehirAdi": "SİNOP",
      "SehirAdiEn": null,
      "UlkeAdi": "TÜRKİYE",
      "UlkeAdiEn": null
    }
  },
  {
    "bayramNamazVakti": {
      "KurbanBayramNamaziHTarihi": "10 Zilhicce 1446",
      "KurbanBayramNamaziSaati": "05:40:00",
      "KurbanBayramNamaziTarihi": "6 Haziran 2025 Cuma",
      "RamazanBayramNamaziHTarihi": "1 Şevval 1446",
      "RamazanBayramNamaziSaati": "06:57:00",
      "RamazanBayramNamaziTarihi": "30 Mart 2025 Pazar"
    },
    "ilceBilgisi": {
      "CografiKibleAcisi": "167",
      "IlceAdi": "SİNOP",
      "IlceAdiEn": null,
      "IlceID": "9847",
      "KabeyeUzaklik": "2332",
      "KibleAcisi": "162",
      "SehirAdi": "SİNOP",
      "SehirAdiEn": null,
      "UlkeAdi": "TÜRKİYE",
      "UlkeAdiEn": null
    }
  },
  {
    "bayramNamazVakti": {
      "KurbanBayramNamaziHTarihi": "10 Zilhicce 1446",
      "KurbanBayramNamaziSaati": "05:44:00",
      "KurbanBayramNamaziTarihi": "6 Haziran 2025 Cuma",
      "RamazanBayramNamaziHTarihi": "1 Şevval 1446",
      "RamazanBayramNamaziSaati": "07:01:00",
      "RamazanBayramNamaziTarihi": "30 Mart 2025 Pazar"
    },
    "ilceBilgisi": {
      "CografiKibleAcisi": "165",
      "IlceAdi": "TÜRKELİ",
      "IlceAdiEn": null,
      "IlceID": "9848",
      "KabeyeUzaklik": "2338",
      "KibleAcisi": "160",
      "SehirAdi": "SİNOP",
      "SehirAdiEn": null,
      "UlkeAdi": "TÜRKİYE",
      "UlkeAdiEn": null
    }
  }
]